PostmanZhongwenWendang/README.md
PostmanZhongwenWendang/__init__.py
PostmanZhongwenWendang/__main__.py
PostmanZhongwenWendang/file.epub
PostmanZhongwenWendang/index.html
PostmanZhongwenWendang/css/__init__.py
PostmanZhongwenWendang/css/annotations.css
PostmanZhongwenWendang/css/main.css
PostmanZhongwenWendang/css/normalize.css
PostmanZhongwenWendang/css/popup.css
PostmanZhongwenWendang/font/__init__.py
PostmanZhongwenWendang/font/fontello.eot
PostmanZhongwenWendang/font/fontello.svg
PostmanZhongwenWendang/font/fontello.ttf
PostmanZhongwenWendang/font/fontello.woff
PostmanZhongwenWendang/img/__init__.py
PostmanZhongwenWendang/img/annotator-glyph-sprite.png
PostmanZhongwenWendang/img/annotator-icon-sprite.png
PostmanZhongwenWendang/img/apple-touch-icon.png
PostmanZhongwenWendang/img/cancelfullscreen.png
PostmanZhongwenWendang/img/close.png
PostmanZhongwenWendang/img/fullscreen.png
PostmanZhongwenWendang/img/loader.gif
PostmanZhongwenWendang/img/menu-icon.png
PostmanZhongwenWendang/img/save.png
PostmanZhongwenWendang/img/saved.png
PostmanZhongwenWendang/img/settings-s.png
PostmanZhongwenWendang/img/settings.png
PostmanZhongwenWendang/img/star.png
PostmanZhongwenWendang/js/__init__.py
PostmanZhongwenWendang/js/epub.js
PostmanZhongwenWendang/js/epub.min.js
PostmanZhongwenWendang/js/epub.min.map
PostmanZhongwenWendang/js/hooks.min.js
PostmanZhongwenWendang/js/hooks.min.map
PostmanZhongwenWendang/js/reader.js
PostmanZhongwenWendang/js/reader.js.map
PostmanZhongwenWendang/js/reader.min.js
PostmanZhongwenWendang/js/reader.min.map
PostmanZhongwenWendang/js/hooks/__init__.py
PostmanZhongwenWendang/js/hooks/extensions/__init__.py
PostmanZhongwenWendang/js/hooks/extensions/highlight.js
PostmanZhongwenWendang/js/libs/__init__.py
PostmanZhongwenWendang/js/libs/jquery.min.js
PostmanZhongwenWendang/js/libs/localforage.min.js
PostmanZhongwenWendang/js/libs/screenfull.js
PostmanZhongwenWendang/js/libs/screenfull.min.js
PostmanZhongwenWendang/js/libs/zip.min.js
postman_zhongwen_wendang-2024.3.4.0.dist-info/METADATA
postman_zhongwen_wendang-2024.3.4.0.dist-info/WHEEL
postman_zhongwen_wendang-2024.3.4.0.dist-info/entry_points.txt
postman_zhongwen_wendang-2024.3.4.0.dist-info/top_level.txt
postman_zhongwen_wendang-2024.3.4.0.dist-info/RECORD
